ugbio_featuremap/__init__.py
ugbio_featuremap/aggregate_lists.awk
ugbio_featuremap/annotate_featuremap.py
ugbio_featuremap/create_somatic_featuremap.py
ugbio_featuremap/explode_lists.awk
ugbio_featuremap/featuremap_consensus_utils.py
ugbio_featuremap/featuremap_to_dataframe.py
ugbio_featuremap/featuremap_utils.py
ugbio_featuremap/featuremap_xgb_prediction.py
ugbio_featuremap/filter_dataframe.py
ugbio_featuremap/integrate_mpileup_to_sfm.py
ugbio_featuremap/pileup_featuremap.py
ugbio_featuremap/somatic_featuremap_fields_transformation.py
ugbio_featuremap/somatic_featuremap_inference_utils.py
ugbio_featuremap/somatic_featuremap_utils.py
ugbio_featuremap-1.20.0.dist-info/METADATA
ugbio_featuremap-1.20.0.dist-info/WHEEL
ugbio_featuremap-1.20.0.dist-info/entry_points.txt
ugbio_featuremap-1.20.0.dist-info/top_level.txt
ugbio_featuremap-1.20.0.dist-info/RECORD
