Metadata-Version: 2.4
Name: ugbio_featuremap
Version: 1.20.0
Summary: Ultima Genomics FeatureMap utils
Author-email: Itai Rusinek <itai.rusinek@ultimagen.com>, Gat Krieger <gat.krieger@ultimagen.com>, Avigail Moldovan <avigail.moldovan@ultimagen.com>
License: Apache-2.0
Requires-Python: >=3.11
Requires-Dist: ugbio_core[ml,vcfbed]
Requires-Dist: ugbio_ppmseq
Requires-Dist: polars>=1.27.1
